doubao_crypt
