Metadata-Version: 2.1
Name: doubao-crypt
Version: 1.1.1
Summary: doubao crypt python library
Home-page: UNKNOWN
Author: biao.xu
Author-email: biao.xu@baodanyun-inc.com
License: UNKNOWN
Platform: UNKNOWN
Classifier: Operating System :: OS Independent
Classifier: Programming Language :: Python :: 3.5
Classifier: Programming Language :: Python :: 3.6
Classifier: Programming Language :: Python :: 3.7
Requires-Python: >=3.5.3
